happy_repo/__init__.py
happy_repo/cli.py
happy_repo/happy_repo.py
happy_repo-0.1.4.dist-info/AUTHORS.rst
happy_repo-0.1.4.dist-info/LICENSE
happy_repo-0.1.4.dist-info/METADATA
happy_repo-0.1.4.dist-info/WHEEL
happy_repo-0.1.4.dist-info/entry_points.txt
happy_repo-0.1.4.dist-info/top_level.txt
happy_repo-0.1.4.dist-info/RECORD
