Metadata-Version: 2.1
Name: happy-repo
Version: 0.1.4
Summary: This is a test range package. This will be destroyed and everything in it.
Home-page: https://github.com/orenkot/happy_repo
Author: Oren Kot
Author-email: przemyslaw.kot@gmail.com
License: MIT license
Keywords: happy_repo
Platform: UNKNOWN
Classifier: Development Status :: 2 - Pre-Alpha
Classifier: Intended Audience :: Developers
Classifier: License :: OSI Approved :: MIT License
Classifier: Natural Language :: English
Classifier: Programming Language :: Python :: 3.6
Classifier: Programming Language :: Python :: 3.7
Requires-Python: >=3.6
Requires-Dist: Click (>=7.0)
